LICENSE.txt
MANIFEST.in
README
README.md
setup.cfg
setup.py
airbnb_script/__init__.py
airbnb_script/airbnb_script.py
airbnb_script.egg-info/PKG-INFO
airbnb_script.egg-info/SOURCES.txt
airbnb_script.egg-info/dependency_links.txt
airbnb_script.egg-info/entry_points.txt
airbnb_script.egg-info/not-zip-safe
airbnb_script.egg-info/requires.txt
airbnb_script.egg-info/top_level.txt
data/data_file